{
  "fighter_profile": {
    "name_th": "เมห์ดาด คานซาเดห์",
    "name_en": "Mehrdad Khanzadeh",
    "alias": "Black Wolf",
    "image_url": "https://res.cloudinary.com/dia2yts2f/image/upload/v1773127424/%E0%B9%80%E0%B8%A1%E0%B8%AB%E0%B9%8C%E0%B8%94%E0%B8%B2%E0%B8%94_%E0%B8%84%E0%B8%B2%E0%B8%99%E0%B8%8B%E0%B8%B2%E0%B9%80%E0%B8%94%E0%B8%AB%E0%B9%8C_hsgdjg.png",
    "grade": "ไม่ระบุ",
    "fighting_style_th": "ไม่ระบุ",
    "fighting_style_en": "ไม่ระบุ",
    "stance": "ไม่ระบุ",
    "physical_stats": {
      "weight_lbs": 124,
      "weight_kg": 56.25,
      "division": "Strawweight",
      "height_ft": "5'6\"",
      "height_cm": 170,
      "reach_cm": "ไม่ระบุ",
      "leg_reach_cm": "ไม่ระบุ"
    },
    "performance_stats": {
      "significant_strikes_per_minute": {
        "head": "ไม่ระบุ",
        "body": "ไม่ระบุ",
        "legs": "ไม่ระบุ",
        "total_accuracy": "ไม่ระบุ"
      },
      "significant_strike_accuracy": {
        "overall_accuracy_percentage": "ไม่ระบุ",
        "accuracy_by_target_percentage": {
          "head": "ไม่ระบุ",
          "body": "ไม่ระบุ",
          "legs": "ไม่ระบุ"
        }
      },
      "defensive_stats": {
        "overall_defense_percentage": "ไม่ระบุ",
        "distance_control_percentage": "ไม่ระบุ",
        "defense_by_target_percentage": {
          "head": "ไม่ระบุ",
          "body": "ไม่ระบุ",
          "legs": "ไม่ระบุ"
        }
      }
    },
    "personal_info": {
      "country_th": "อิหร่าน",
      "country_en": "Iran",
      "age": 25,
      "team_th": "ไฟต์ เนชัน หัวหิน (Fight Nation Hua Hin)",
      "team_en": "Fight Nation Hua Hin"
    },
    "target_url": "",
    "target_urls": [
      "https://www.onefc.com/th/athletes/mehrdad-khanzadeh/"
    ]
  },
  "fight_history": [
    {
      "result": "Loss",
      "discipline_en": "Muay Thai",
      "method_en": "Unanimous Decision",
      "round": 3,
      "time": "3:00",
      "opponent_th": "ก้องชัย ไฉนดอนเมือง",
      "opponent_en": "",
      "opponent_country": "ไทย",
      "date": "Mar 27, 2026",
      "rating": 5,
      "event_en": "ONE ลุมพินี 148 & The Inner Circle"
    },
    {
      "result": "Win",
      "discipline_en": "Muay Thai",
      "method_en": "Split Decision",
      "round": 3,
      "time": "3:00",
      "opponent_th": "กริชเพชร พีเค.แสนชัย",
      "opponent_en": "",
      "opponent_country": "ไทย",
      "date": "Sep 19, 2025",
      "rating": 5,
      "event_en": "ONE ลุมพินี 125"
    },
    {
      "result": "Loss",
      "discipline_en": "Muay Thai",
      "method_en": "Unanimous Decision",
      "round": 3,
      "time": "3:00",
      "opponent_th": "พิชิตชัย พีเค.แสนชัย",
      "opponent_en": "",
      "opponent_country": "ไทย",
      "date": "Jan 19, 2024",
      "rating": 5,
      "event_en": "ONE ลุมพินี 48"
    },
    {
      "result": "Win",
      "discipline_en": "Muay Thai",
      "method_en": "Unanimous Decision",
      "round": 3,
      "time": "3:00",
      "opponent_th": "ยางดำ จิตรเมืองนนท์",
      "opponent_en": "",
      "opponent_country": "ไทย",
      "date": "Nov 10, 2023",
      "rating": 5,
      "event_en": "ONE ลุมพินี 40"
    }
  ],
  "fight_history_one_championship": [],
  "upcoming_fights": [],
  "weigh_in_history": [
    {
      "event_name": "ONE ลุมพินี 148",
      "weight_lbs": 124,
      "division": "Strawweight"
    }
  ]
}